uscalendar/__init__.py
uscalendar/federal_holiday.py
uscalendar/helpers.py
uscalendar/market_open.py
uscalendar-0.0.2.dist-info/LICENSE
uscalendar-0.0.2.dist-info/METADATA
uscalendar-0.0.2.dist-info/WHEEL
uscalendar-0.0.2.dist-info/top_level.txt
uscalendar-0.0.2.dist-info/RECORD
