Metadata-Version: 2.1
Name: uscalendar
Version: 0.0.2
Summary: Package that contains modules for US Federal Holidays and US Market Opens
Home-page: https://github.com/mmcelhan/us_calendar_source
Author: Matthew McElhaney
Author-email: matt@lamplightlab.com
License: UNKNOWN
Project-URL: blog post, https://lamplightlab.com/2022/01/27/end-to-end-guide-for-creating-python-packages/
Platform: UNKNOWN
Classifier: Programming Language :: Python :: 3
Classifier: License :: OSI Approved :: MIT License
Classifier: Operating System :: OS Independent
Requires-Python: >=3.6
License-File: LICENSE
